wpe/build_agent.py
wpe/cli.py
wpe/constants.py
wpe/core.py
wpe/deployment.py
wpe/global_config.py
wpe/hook_processor.py
wpe/jb_run_manager.py
wpe/parameter.py
wpe/pathman.py
wpe/plugin_test_runner.py
wpe/project_config.py
wpe/renamer.py
wpe/templates/.wpe/hooks/post_build.py
wpe/templates/.wpe/hooks/pre_full_pack.py
wpe/templates/.wpe/hooks/pre_premake.py
wpe/templates/.wpe/wpe_project.toml
wpe/templates/_idea/JetBrainsRunConfig.xml
wpe/templates/SoundEnginePlugin/ProjectNameMeta.cpp
wpe/templates/SoundEnginePlugin/ProjectNameMeta.h
wpe/templates/SoundEnginePlugin/ProjectNameParams.cpp
wpe/templates/SoundEnginePlugin/ProjectNameParams.h
wpe/templates/test/.gitignore
wpe/templates/test/CMakeLists.txt
wpe/templates/test/main.cpp
wpe/templates/test/util/test_mem_alloc.hpp
wpe/templates/test/util/test_util.hpp
wpe/templates/WwisePlugin/ProjectName.rc
wpe/templates/WwisePlugin/ProjectNamePlugin.cpp
wpe/templates/WwisePlugin/ProjectNamePlugin.h
wpe/templates/WwisePlugin/resource.h
wpe/templates/WwisePlugin/Win32/ProjectNamePluginGUI.cpp
wpe/templates/WwisePlugin/Win32/ProjectNamePluginGUI.h
wpe/util.py
wpe/wp_patch/build.py
wpe/wp_patch/common/command/android.py
wpe/wp_patch/common/platform/__init__.py
wpe/wp_patch/common/platform/android.py
wpe/wp_patch/common/platform/ps5.py
wpe/wp_patch/package.py
wpe/wp_patch/premake.py
wpe/wp_patch/premakePlugins.lua
wpe/wp_wrapper.py
wp_enhanced-1.0.5.dist-info/entry_points.txt
wp_enhanced-1.0.5.dist-info/LICENSE
wp_enhanced-1.0.5.dist-info/METADATA
wp_enhanced-1.0.5.dist-info/WHEEL
wp_enhanced-1.0.5.dist-info/RECORD
