Metadata-Version: 2.1
Name: wp-enhanced
Version: 1.0.5
Summary: Wrapper of `wp.py`. Easy to premake, build, and deploy wwise plugins.
Home-page: https://github.com/tgalpha/wp-enhanced
License: MIT
Author: tgalpha
Author-email: tanalpha.zhy@gmail.com
Requires-Python: >=3.9,<4.0
Classifier: License :: OSI Approved :: MIT License
Classifier: Programming Language :: Python :: 3
Classifier: Programming Language :: Python :: 3.9
Classifier: Programming Language :: Python :: 3.10
Classifier: Programming Language :: Python :: 3.11
Requires-Dist: Flask (>=3.0.3,<4.0.0)
Requires-Dist: jinja2 (>=3.1.2,<4.0.0)
Requires-Dist: kkpyutil (>=1.33.5,<2.0.0)
Requires-Dist: lupa (>=2.1,<3.0)
Requires-Dist: markdown (>=3.4.4,<4.0.0)
Requires-Dist: packaging (>=24.1,<25.0)
Requires-Dist: requests (>=2.31.0,<3.0.0)
Requires-Dist: toml (>=0.10.2,<0.11.0)
Requires-Dist: werkzeug (==3.0.3)
Project-URL: Repository, https://github.com/tgalpha/wp-enhanced
